{
    "Animator": {
        "Enabled": true,
        "controllerPath": "Resources/Game/Animations/NewController.json",
        "currentState": "Empty",
        "isPlaying": true
    },
    "Children": [],
    "Collider": {
        "Enabled": true,
        "boxSize": [
            1.0,
            1.0,
            1.0
        ],
        "height": 2.0,
        "isTrigger": false,
        "layer": 2,
        "offset": [
            0.0,
            0.0,
            0.0
        ],
        "radius": 0.5,
        "type": 2
    },
    "ID": 1,
    "MeshComponent": {
        "Enabled": true,
        "color": [
            1.0,
            1.0,
            1.0,
            1.0
        ],
        "modelKey": "Player/Y Bot.fbx",
        "scaleOffset": [
            0.029999999329447746,
            0.029999999329447746,
            0.029999999329447746
        ]
    },
    "PlayerInput": {
        "Enabled": true,
        "jumpPower": 5.0,
        "speed": 3.0
    },
    "PlayerMoveData": {
        "Enabled": true,
        "speed": 10.0
    },
    "Relationship": {
        "Enabled": true,
        "children": [],
        "parent": 4294967295
    },
    "Rigidbody": {
        "Enabled": true,
        "drag": 0.10000000149011612,
        "mass": 1.0,
        "type": 1,
        "useGravity": true
    },
    "Tag": {
        "Enabled": true,
        "componentOrder": [
            "Collider",
            "PlayerInput",
            "Rigidbody",
            "Tag",
            "Transform",
            "PlayerMoveData",
            "MeshComponent",
            "Animator",
            "Relationship"
        ],
        "name": "Player"
    },
    "Transform": {
        "Enabled": true,
        "position": [
            -1.8807264566421509,
            2.255858898162842,
            0.0
        ],
        "rotation": [
            0.0,
            -0.0,
            0.0
        ],
        "scale": [
            1.0,
            1.0,
            1.0
        ]
    }
}
